mgnify_ro_crates/__init__.py
mgnify_ro_crates/motus_ro_crates_preparer.py
mgnify_ro_crates/ro_crate_ui_assets_provider.py
mgnify_ro_crates-0.1.2.dist-info/LICENSE
mgnify_ro_crates-0.1.2.dist-info/METADATA
mgnify_ro_crates-0.1.2.dist-info/WHEEL
mgnify_ro_crates-0.1.2.dist-info/entry_points.txt
mgnify_ro_crates-0.1.2.dist-info/top_level.txt
mgnify_ro_crates-0.1.2.dist-info/RECORD
