Metadata-Version: 2.1
Name: mgnify_ro_crates
Version: 0.1.2
Summary: A packge for creating browsable RO-Crates from pipeline results
Home-page: https://github.com/EBI-Metagenomics/mgnify-ro-crates.git
Author: Mahfouz Shehu, Aleksander Rajkovic, Sandy  Rogers
Author-email: mahfouz@ebi.ac.uk, metagenomics@ebi.ac.uk
Classifier: Programming Language :: Python :: 3
Classifier: License :: OSI Approved :: MIT License
Classifier: Operating System :: OS Independent
Requires-Python: >=3.6
License-File: LICENSE
Requires-Dist: tqdm
Requires-Dist: requests
Requires-Dist: beautifulsoup4
Requires-Dist: arcp
